rss_parser/__init__.py
rss_parser/helpers.py
rss_parser/rss_parser.py
rss_parser/argument_parser/__init__.py
rss_parser/argument_parser/argument_parser.py
rss_parser/html_saver/__init__.py
rss_parser/html_saver/html_converter.py
rss_parser/json_converter/__init__.py
rss_parser/json_converter/json_converter.py
rss_parser/news_cache/__init__.py
rss_parser/news_cache/create_cache.py
rss_parser/pdf_saver/__init__.py
rss_parser/pdf_saver/pdf_converter.py
rss_reader_ellypro-4.0.0.dist-info/LICENSE
rss_reader_ellypro-4.0.0.dist-info/METADATA
rss_reader_ellypro-4.0.0.dist-info/WHEEL
rss_reader_ellypro-4.0.0.dist-info/entry_points.txt
rss_reader_ellypro-4.0.0.dist-info/top_level.txt
rss_reader_ellypro-4.0.0.dist-info/RECORD
