Metadata-Version: 2.1
Name: rss-reader-ellypro
Version: 4.0.0
Summary: This cmd tool is intended to read rss-feed from realpython.com
Home-page: https://github.com/EllyPro
Author: Elyorbek Hamroyev
Author-email: pro100elly@gmail.com
License: MIT
Platform: UNKNOWN
Classifier: Programming Language :: Python :: 3.8
Classifier: Operating System :: OS Independent
Requires-Python: >=3.7
License-File: LICENSE
Requires-Dist: beautifulsoup4 (==4.10.0)
Requires-Dist: fpdf (==1.7.2)
Requires-Dist: lxml (==4.8.0)
Requires-Dist: requests (==2.27.1)
